Metadata-Version: 2.1
Name: https-finder
Version: 0.1
Summary: this script can search for https proxies and immediately checks them for validity
Home-page: UNKNOWN
Author-email: Prostoegorich2@gmail.com
License: UNKNOWN
Platform: UNKNOWN
